<annotation>
	<folder>20191129_M02_07h24</folder>
	<filename>20191129_M02_07h24-30.jpg</filename>
	<path>/home/mina/PythonLibs/data-trainning/source_images/20191129_M02_07h24/20191129_M02_07h24-30.jpg</path>
	<source>
		<database>Unknown</database>
	</source>
	<size>
		<width>1280</width>
		<height>720</height>
		<depth>3</depth>
	</size>
	<segmented>0</segmented>
	<object>
		<name>parcel</name>
		<pose>Unspecified</pose>
		<truncated>0</truncated>
		<difficult>0</difficult>
		<bndbox>
			<xmin>733</xmin>
			<ymin>330</ymin>
			<xmax>812</xmax>
			<ymax>391</ymax>
		</bndbox>
	</object>
	<object>
		<name>parcel</name>
		<pose>Unspecified</pose>
		<truncated>0</truncated>
		<difficult>0</difficult>
		<bndbox>
			<xmin>742</xmin>
			<ymin>416</ymin>
			<xmax>818</xmax>
			<ymax>492</ymax>
		</bndbox>
	</object>
	<object>
		<name>parcel</name>
		<pose>Unspecified</pose>
		<truncated>0</truncated>
		<difficult>0</difficult>
		<bndbox>
			<xmin>760</xmin>
			<ymin>505</ymin>
			<xmax>827</xmax>
			<ymax>558</ymax>
		</bndbox>
	</object>
	<object>
		<name>parcel</name>
		<pose>Unspecified</pose>
		<truncated>0</truncated>
		<difficult>0</difficult>
		<bndbox>
			<xmin>755</xmin>
			<ymin>636</ymin>
			<xmax>821</xmax>
			<ymax>700</ymax>
		</bndbox>
	</object>
</annotation>
